excimer_referencer/__init__.py
excimer_referencer/referencer.py
excimer_referencer-0.8.dist-info/entry_points.txt
excimer_referencer-0.8.dist-info/LICENSE
excimer_referencer-0.8.dist-info/WHEEL
excimer_referencer-0.8.dist-info/METADATA
excimer_referencer-0.8.dist-info/RECORD
